{
	"allemande": ["poulette"],
	"américaine": ["orientale"],
	"bercy": ["marinière"],
	"beurre": ["câpres", "groseilles", "laguipierre"],
	"bordelaise": ["rouennaise"],
	"béarnaise": ["beauharnais", "choron", "paloise", "foyot", "tyrolienne"],
	"béchamel": ["bohémienne", "cardinal", "mornay", "moutarde", "soubise", "crevettes", "crème"],
	"crème": ["écossaise"],
	"demi-glace": [
		"bigarrade",
		"champignons",
		"chaudfroid",
		"diable",
		"duxelles",
		"estragon",
		"financière",
		"godard",
		"grand-veneur",
		"gratin",
		"hussarde",
		"italienne",
		"lyonnaise",
		"madère",
		"moelle",
		"porto",
		"périgourdine",
		"périgueux",
		"régence",
		"salmis",
		"tortue",
		"zingara",
		"bordelaise",
		"robert",
		"poivrade"
	],
	"diplomate": ["riche"],
	"espagnole": [
		"hachée",
		"africaine",
		"bourguignonne",
		"chasseur",
		"génevoise",
		"la vallière",
		"matelote",
		"piquante",
		"romaine",
		"vin rouge",
		"gratin",
		"bercy",
		"demi-glace"
	],
	"foyot": ["colbert"],
	"hollandaise": ["bavaroise", "maltaise", "mousseline", "noisette", "béarnaise"],
	"homard": ["victoria"],
	"mayonnaise": [
		"andalouse",
		"aïoli",
		"chantilly",
		"gribiche",
		"mousquetaire",
		"russe",
		"rémoulade",
		"suédoise",
		"tartare",
		"verte",
		"vincent"
	],
	"normande": ["anchois", "huîtres", "joinville", "véron", "diplomate"],
	"poivrade": ["chevreuil", "diane", "moscovite", "venaison"],
	"robert": ["charcutière"],
	"tomate": ["bolognaise", "milanaise", "portugaise", "hachée", "zingara"],
	"tyrolienne": ["véron"],
	"velouté de poisson": [
		"bonnefoy",
		"bretonne",
		"l'aurore",
		"livonienne",
		"nantua",
		"vénitienne",
		"vin blanc",
		"crevettes",
		"bercy",
		"homard",
		"américaine",
		"normande"
	],
	"velouté de veau": [
		"hongroise",
		"poulette",
		"ravigote chaud",
		"villageoise",
		"villeroy",
		"allemande"
	],
	"velouté de volaille": ["albuféra", "chivry", "ivoire", "suprème"],
	"vin blanc": ["saint-malo", "souchet"],
	"vinaigrette": ["ravigote"]
}
